{
  "project_info": {
    "project_number": "756493988923",
    "firebase_url": "https://votingsystem-6a6ab.firebaseio.com",
    "project_id": "votingsystem-6a6ab",
    "storage_bucket": "votingsystem-6a6ab.appspot.com"
  },
  "client": [
    {
      "client_info": {
        "mobilesdk_app_id": "1:756493988923:android:3b28a2ab9893ff12",
        "android_client_info": {
          "package_name": "com.votingsystem.tsiro.votingsystem"
        }
      },
      "oauth_client": [
        {
          "client_id": "756493988923-8p9kv48ais6pkoojpbak602mbmaud40g.apps.googleusercontent.com",
          "client_type": 3
        }
      ],
      "api_key": [
        {
          "current_key": "AIzaSyDkNllRZQVi550KIrmqCHcvWBvX7wMQgWI"
        }
      ],
      "services": {
        "analytics_service": {
          "status": 1
        },
        "appinvite_service": {
          "status": 1,
          "other_platform_oauth_client": []
        },
        "ads_service": {
          "status": 2
        }
      }
    }
  ],
  "configuration_version": "1"
}